bt/__init__.py
bt/bluetooth_constants.py
bt/bluetooth_exceptions.py
bt/bluetooth_gatt.py
bt/bluetooth_utils.py
bt/bt_connect.py
bt/qr_connect_mipi.py
bt/qr_connect_usb.py
hengbot_api/__init__.py
hengbot_api/sparky.py
hengbot_api-0.1.4.dist-info/LICENSE
hengbot_api-0.1.4.dist-info/METADATA
hengbot_api-0.1.4.dist-info/WHEEL
hengbot_api-0.1.4.dist-info/top_level.txt
hengbot_api-0.1.4.dist-info/RECORD
