Metadata-Version: 2.1
Name: hengbot-api
Version: 0.1.4
Summary: hengbot-api
Author: RMaixtr
Author-email: 53236564@qq.com
License: MIT
Classifier: Programming Language :: Python :: 3
License-File: LICENSE
Requires-Dist: websocket-client
